Workbook

Sheet Summary
A1: Everlast Welders — Action Tracker
A2: Sample for review, prepared Oct 16, 2026. Edit Status, Priority and Due on the Actions sheet; counts below update automatically.
A3: Legend: yellow cells on the Actions sheet are the ones to edit (Status, Priority, Due).
A5: Measure | B5: Count
A6: Open actions (not Done) | B6: =COUNTA(Actions!A2:A200)-COUNTIF(Actions!H2:H200,"Done") -> 30
A7: Priority 1 open | B7: =COUNTIFS(Actions!D2:D200,"P1",Actions!H2:H200,"<>Done") -> 16
A8: Priority 2 open | B8: =COUNTIFS(Actions!D2:D200,"P2",Actions!H2:H200,"<>Done") -> 10
A9: Priority 3 open | B9: =COUNTIFS(Actions!D2:D200,"P3",Actions!H2:H200,"<>Done") -> 4
A10: Follow-ups open | B10: =COUNTIFS(Actions!C2:C200,"Follow-up",Actions!H2:H200,"<>Done") -> 6
A11: Open questions | B11: =COUNTIFS(Actions!C2:C200,"Open question",Actions!H2:H200,"<>Done") -> 5
A12: Owner's items open | B12: =COUNTIFS(Actions!E2:E200,"Owner",Actions!H2:H200,"<>Done") -> 11
A13: Overdue (past due, not Done) | B13: =SUMPRODUCT((Actions!F2:F200<>"")*(Actions!F2:F200<TODAY())*(Actions!H2:H200<>"Done")) -> 0
A14: Done | B14: =COUNTIF(Actions!H2:H200,"Done") -> 0

Sheet Actions
A1: ID | B1: Action | C1: Type | D1: Priority | E1: Owner | F1: Due | G1: Days to due | H1: Status | I1: Area | J1: Next step | K1: Playbook
A2: A02 | B2: Confirm QuickBooks Online is the ledger and get accountant access | C2: Follow-up | D2: P1 | E2: Owner | F2: 46315 | G2: =IF(H2="Done","",F2-TODAY()) -> 4 | H2: Waiting | I2: Setup | J2: Owner sends accountant invite from QuickBooks settings | K2: PB-COA
A3: A03 | B3: Accrual or cash basis? Calendar or fiscal year? | C3: Open question | D3: P1 | E3: Owner | F3: 46315 | G3: =IF(H3="Done","",F3-TODAY()) -> 4 | H3: Open | I3: Setup | J3: Confirm with CPA; plan assumes accrual, calendar year | K3: PB-COA
A4: A08 | B4: Is inventory tracked in QuickBooks or a separate system? | C4: Open question | D4: P1 | E4: Owner | F4: 46315 | G4: =IF(H4="Done","",F4-TODAY()) -> 4 | H4: Open | I4: Inventory | J4: Decides how COGS and stock reports are built | K4: PB-INV
A5: A04 | B5: Get access to website store, Amazon and payment processor reports | C5: Follow-up | D5: P1 | E5: Owner | F5: 46316 | G5: =IF(H5="Done","",F5-TODAY()) -> 5 | H5: Waiting | I5: Sales channels | J5: Read-only report access for each channel | K5: PB-REC
A6: A06 | B6: Map current chart of accounts to product-line and channel structure | C6: To-do | D6: P1 | E6: Bookkeeper | F6: 46318 | G6: =IF(H6="Done","",F6-TODAY()) -> 7 | H6: Not started | I6: Setup | J6: Export current accounts; draft mapping for owner review | K6: PB-COA
A7: A05 | B7: Reconcile Q3 2026 (Jul–Sep) bank, card and processor accounts | C7: To-do | D7: P1 | E7: Bookkeeper | F7: 46323 | G7: =IF(H7="Done","",F7-TODAY()) -> 12 | H7: Not started | I7: Reconciliation | J7: Starting point for clean quarterly reports | K7: PB-REC
A8: A01 | B8: Deliver Forecasting & Inventory Operations report for the new-year order | C8: To-do | D8: P1 | E8: Bookkeeper | F8: 46325 | G8: =IF(H8="Done","",F8-TODAY()) -> 14 | H8: In progress | I8: Forecasting | J8: Pull 2025 and 2026 unit sales by SKU; draft reorder quantities | K8: PB-INV
A9: A16 | B9: Seasonal Inventory sample: stock on hand vs last Nov–Dec sales by SKU | C9: To-do | D9: P1 | E9: Bookkeeper | F9: 46328 | G9: =IF(H9="Done","",F9-TODAY()) -> 17 | H9: Not started | I9: Inventory | J9: Flag SKUs at risk of selling out before Christmas | K9: PB-INV
A10: A14 | B10: Deliver Q3 Financial & Cost Intelligence report | C10: To-do | D10: P1 | E10: Bookkeeper | F10: 46332 | G10: =IF(H10="Done","",F10-TODAY()) -> 21 | H10: Not started | I10: Reporting | J10: Depends on Q3 reconciliation | K10: PB-CLOSE
A11: A15 | B11: Deliver Q3 Sales & Pricing report | C11: To-do | D11: P1 | E11: Bookkeeper | F11: 46332 | G11: =IF(H11="Done","",F11-TODAY()) -> 21 | H11: Not started | I11: Reporting | J11: Margin by product line and channel | K11: PB-CLOSE
A12: A18 | B12: October month-end close | C12: To-do | D12: P1 | E12: Bookkeeper | F12: 46339 | G12: =IF(H12="Done","",F12-TODAY()) -> 28 | H12: Not started | I12: Close | J12: Target: business day 10 | K12: PB-CLOSE
A13: A21 | B13: November month-end close | C13: To-do | D13: P1 | E13: Bookkeeper | F13: 46370 | G13: =IF(H13="Done","",F13-TODAY()) -> 59 | H13: Not started | I13: Close | J13: Target: business day 10 | K13: PB-CLOSE
... A31: A29 | B31: Social Media & Demand Generation sample | C31: To-do | D31: P3 | E31: Bookkeeper | F31: 46339 | G31: =IF(H31="Done","",F31-TODAY()) -> 28 | H31: Not started | I31: Reporting | J31: Ad spend vs sales by channel | K31: PB-INV

Sheet Playbooks
A1: Playbook | B1: Title | C1: Frequency | D1: Step | E1: Instruction | F1: Owner | G1: Done?
A2: PB-CLOSE | B2: Month-end close | C2: Monthly | D2: 1 | E2: Reconcile every bank, credit card and loan account | F2: Bookkeeper
A3: PB-CLOSE | B3: Month-end close | C3: Monthly | D3: 2 | E3: Clear each processor and marketplace clearing account | F3: Bookkeeper
A4: PB-CLOSE | B4: Month-end close | C4: Monthly | D4: 3 | E4: Receive all inventory shipments and post landed costs | F4: Bookkeeper
A5: PB-CLOSE | B5: Month-end close | C5: Monthly | D5: 4 | E5: Post inventory adjustments from counts and returns | F5: Bookkeeper
A6: PB-CLOSE | B6: Month-end close | C6: Monthly | D6: 5 | E6: Accrue warranty reserve and unpaid bills | F6: Bookkeeper
A7: PB-CLOSE | B7: Month-end close | C7: Monthly | D7: 6 | E7: Review AR and AP aging for errors and stale items | F7: Bookkeeper
A8: PB-CLOSE | B8: Month-end close | C8: Monthly | D8: 7 | E8: Confirm sales tax liability matches filed returns | F8: Bookkeeper
A9: PB-CLOSE | B9: Month-end close | C9: Monthly | D9: 8 | E9: Review P&L and balance sheet vs last month and last year | F9: Owner
A10: PB-CLOSE | B10: Month-end close | C10: Monthly | D10: 9 | E10: Lock the period in QuickBooks | F10: Bookkeeper
A11: PB-CLOSE | B11: Month-end close | C11: Monthly | D11: 10 | E11: Deliver the monthly reporting packet | F11: Bookkeeper
A12: PB-REC | B12: Sales channel reconciliation | C12: Weekly and monthly | D12: 1 | E12: Record gross sales by product line from each channel's report | F12: Bookkeeper
A13: PB-REC | B13: Sales channel reconciliation | C13: Weekly and monthly | D13: 2 | E13: Record fees, refunds, chargebacks and shipping as separate lines | F13: Bookkeeper
... A46: PB-COA | B46: Chart of accounts setup | C46: Once, then yearly | D46: 5 | E46: Owner reviews and approves the new structure | F46: Owner

Sheet Close checklist
A1: Business day | B1: Step | C1: Owner | D1: Oct close | E1: Nov close | F1: Dec close
A2: 1 | B2: Reconcile every bank, credit card and loan account | C2: Bookkeeper
A3: 2 | B3: Clear each processor and marketplace clearing account | C3: Bookkeeper
A4: 3 | B4: Receive all inventory shipments and post landed costs | C4: Bookkeeper
A5: 4 | B5: Post inventory adjustments from counts and returns | C5: Bookkeeper
A6: 5 | B6: Accrue warranty reserve and unpaid bills | C6: Bookkeeper
A7: 6 | B7: Review AR and AP aging for errors and stale items | C7: Bookkeeper
A8: 7 | B8: Confirm sales tax liability matches filed returns | C8: Bookkeeper
A9: 8 | B9: Review P&L and balance sheet vs last month and last year | C9: Owner
A10: 9 | B10: Lock the period in QuickBooks | C10: Bookkeeper
A11: 10 | B11: Deliver the monthly reporting packet | C11: Bookkeeper
B12: Steps done (mark each with ✓) | D12: =COUNTA(D2:D11)&" of 10" -> 0 of 10 | E12: =COUNTA(E2:E11)&" of 10" -> 0 of 10 | F12: =COUNTA(F2:F11)&" of 10" -> 0 of 10
A15: Due: Oct close Nov 13, 2026 · Nov close Dec 14, 2026 · Dec close and year-end packet Jan 15, 2027

Sheet Operating rhythm
A1: Frequency | B1: Task
A2: Daily | B2: Categorize bank and card feeds
A3: Daily | B3: Record customer deposits
A4: Daily | B4: Flag large or unusual transactions
A5: Weekly | B5: Import sales summaries from each channel
A6: Weekly | B6: Enter and code vendor bills
A7: Weekly | B7: Send dealer invoices; chase past-due
A8: Weekly | B8: Match processor payouts to deposits
A9: Monthly | B9: Reconcile bank, card and processor accounts
A10: Monthly | B10: Post inventory and COGS adjustments
A11: Monthly | B11: Accrue warranty reserve
A12: Monthly | B12: Record payroll by department
... A22: Annually | B22: Year-end packet for the CPA
